{
  "domain": "printing",
  "faqs": [
    {
      "keywords": ["料金", "価格", "いくら", "費用"],
      "question": "印刷料金はいくらですか？",
      "answer": "印刷料金は、印刷物の種類・サイズ・部数・用紙・加工によって変わります。詳細なお見積もりは無料で作成いたしますので、まずはご希望の仕様をお聞かせください。"
    },
    {
      "keywords": ["納期", "いつまで", "日数", "期間"],
      "question": "納期はどのくらいかかりますか？",
      "answer": "通常、データ入稿後3〜5営業日で納品可能です。特急印刷の場合は最短翌日納品も対応しております。部数や仕様により変動しますので、詳しくはお問い合わせください。"
    },
    {
      "keywords": ["データ", "入稿", "形式", "ファイル"],
      "question": "入稿データの形式は？",
      "answer": "PDF、AI（Illustrator）、PSD（Photoshop）形式に対応しています。Office系ソフトのデータも変換作業込みで承ります。データ作成のご相談も可能です。"
    },
    {
      "keywords": ["最小", "ロット", "少部数", "小ロット"],
      "question": "最小ロットは何部からですか？",
      "answer": "チラシ・パンフレットは100部から、名刺は50枚から承っております。小ロット印刷もお気軽にご相談ください。"
    },
    {
      "keywords": ["サンプル", "見本", "実物"],
      "question": "サンプルは見られますか？",
      "answer": "はい、過去の制作実績のサンプルをご覧いただけます。用紙見本もご用意しておりますので、お気軽にお申し付けください。"
    }
  ]
}